rtl/include/definitions.svh
/**
************************************************************************************************************************
* @file    definitions.svh
* @author  Hugo Becerril
* @email   vhugobeb@gmail.com
* @brief   Definition of the project
************************************************************************************************************************
* @Description
* This is an example of header file for declareate datatypes and macros
*
************************************************************************************************************************
*/

/**********************************************************************************************************************/
/*                          START OF HEADER                                                                           */
/**********************************************************************************************************************/
`ifndef DEFINITIONS_SVH_
`define DEFINITIONS_SVH_

/**********************************************************************************************************************/
/*                          START OF DEFINES                                                                          */
/**********************************************************************************************************************/
/**********************************************************************************************************************/
/*                          END OF DEFINES                                                                            */
/**********************************************************************************************************************/

/**********************************************************************************************************************/
/*                           START OF MACROS                                                                          */
/**********************************************************************************************************************/
/**********************************************************************************************************************/
/*                           END OF MACROS                                                                            */
/**********************************************************************************************************************/

/**********************************************************************************************************************/
/*                          START OF DATATYPES                                                                        */
/**********************************************************************************************************************/
/*
* @brief:        Bus_t structure definition
* @description:  This contains a Tag and Data value
*/
typedef struct packed {
    logic [ 3 : 0 ] Tag;
    logic [ 7 : 0 ] Data;
} bus_t;
/**********************************************************************************************************************/
/*                          END OF DATATYPES                                                                          */
/**********************************************************************************************************************/

`endif    /* DEFINITIONS_SVH_ */
/**********************************************************************************************************************/
/*                          END OF HEADER                                                                             */
/**********************************************************************************************************************/

rtl/mod_main.sv
/**
************************************************************************************************************************
* @file    mod_main.sv
* @author  Hugo Becerril
* @email   vhugobeb@gmail.com
* @brief   This is a simple example of a D type flip flop as the
*          main module of the project.
************************************************************************************************************************
* @Description
* This is a simple example of a D-type flip flop as the main module of the project. Where the data type that goes
* through the circuit is composed of a tag and a data, this data type is declared in the definitions.svh file.
*
************************************************************************************************************************
*/

/**********************************************************************************************************************/
/*                          START OF INCLUDES                                                                         */
/**********************************************************************************************************************/
`include "definitions.svh"
/**********************************************************************************************************************/
/*                          END OF INCLUDES                                                                           */
/**********************************************************************************************************************/

/**********************************************************************************************************************/
/*                          START OF MAIN MODULE                                                                      */
/**********************************************************************************************************************/
module mod_main (
    // Inputs
    input        i_clk, // Clock Signal
    input          i_E, // Enable Signal
    input  bus_t   i_D, // Data Input
    // Outputs
    output bus_t   o_Q, // Data Output
    output bus_t  o_nQ  // Output data inverted
);

    /******************************************************************************************************************/
    /*                      START OF REGISTERS                                                                        */
    /******************************************************************************************************************/
    /******************************************************************************************************************/
    /*                      END OF REGISTERS                                                                          */
    /******************************************************************************************************************/

    /******************************************************************************************************************/
    /*                      START OF WIRES                                                                            */
    /******************************************************************************************************************/
    /******************************************************************************************************************/
    /*                      END OF WIRES                                                                              */
    /******************************************************************************************************************/

    /******************************************************************************************************************/
    /*                      START OF BITS                                                                             */
    /******************************************************************************************************************/
    /******************************************************************************************************************/
    /*                      END OF BITS                                                                               */
    /******************************************************************************************************************/

    /******************************************************************************************************************/
    /*                      START OF INITIAL BLOCK                                                                    */
    /******************************************************************************************************************/
    /******************************************************************************************************************/
    /*                      START OF INITIAL BLOCK                                                                    */
    /******************************************************************************************************************/


    /******************************************************************************************************************/
    /*                      START OF SEQUENTIAL PROCESS                                                               */
    /******************************************************************************************************************/
    always_ff @( posedge i_clk ) begin : D_Type_Flip_Flop
        if ( i_E ) begin
            o_Q  <= i_D;
        end
        else begin
            o_Q <= bus_t'{Tag: 0, Data: 0};
        end
    end : D_Type_Flip_Flop
    /******************************************************************************************************************/
    /*                      END OF SEQUENTIAL PROCESS                                                                 */
    /******************************************************************************************************************/

    /******************************************************************************************************************/
    /*                      START OF COMBINATORIAL PROCESS                                                            */
    /******************************************************************************************************************/
    assign o_nQ = ~o_Q;
    /******************************************************************************************************************/
    /*                      END OF COMBINATORIAL PROCESS                                                              */
    /******************************************************************************************************************/

endmodule
/**********************************************************************************************************************/
/*                          END OF MAIN MODULE                                                                        */
/**********************************************************************************************************************/

tb_sim/waveform.vcd
$version Generated by VerilatedVcd $end
$timescale 1ps $end
 $scope module TOP $end
  $scope module mod_main $end
   $var wire 1 # i_clk $end
   $var wire 1 $ i_E $end
   $scope module i_D $end
    $var wire 4 % Tag [3:0] $end
    $var wire 8 & Data [7:0] $end
   $upscope $end
   $scope module o_Q $end
    $var wire 4 ' Tag [3:0] $end
    $var wire 8 ( Data [7:0] $end
   $upscope $end
   $scope module o_nQ $end
    $var wire 4 ) Tag [3:0] $end
    $var wire 8 * Data [7:0] $end
   $upscope $end
  $upscope $end
 $upscope $end
$enddefinitions $end


#0
0#
1$
b0000 %
b00000000 &
b0000 '
b00000000 (
b1111 )
b11111111 *
#20
#40
1#
b00000001 &
#60
0#
#80
1#
b0001 %
b00001010 &
#100
0#
#120
1#
b0010 %
b00001011 &
#140
0#
#160
1#
b0011 %
b00001100 &
#180
0#
#200
1#
0$
b0100 %
b00001101 &
b0100 '
b00001101 (
b1011 )
b11110010 *
#220
0#
#240
1#
b0101 %
b00001110 &
b0101 '
b00001110 (
b1010 )
b11110001 *
#260
0#
#280
1#
b0110 %
b00001111 &
b0110 '
b00001111 (
b1001 )
b11110000 *
#300
0#
#320
1#
1$
b0111 %
b00010000 &
b0000 '
b00000000 (
b1111 )
b11111111 *
#340
0#
#360
1#
b0000 %
b00000000 &
